needlestack/__init__.py
needlestack/exceptions.py
needlestack/apis/__init__.py
needlestack/apis/indexing.py
needlestack/apis/serializers.py
needlestack/balancers/__init__.py
needlestack/balancers/greedy.py
needlestack/balancers/knapsack.py
needlestack/cluster_managers/__init__.py
needlestack/cluster_managers/manager.py
needlestack/cluster_managers/zookeeper.py
needlestack/collections/__init__.py
needlestack/collections/collection.py
needlestack/collections/shard.py
needlestack/data_sources/__init__.py
needlestack/data_sources/gcs.py
needlestack/data_sources/local.py
needlestack/data_sources/source.py
needlestack/indices/__init__.py
needlestack/indices/faiss_indices.py
needlestack/indices/index.py
needlestack/servicers/__init__.py
needlestack/servicers/factory.py
needlestack/servicers/logging.py
needlestack/servicers/merger.py
needlestack/servicers/searcher.py
needlestack/servicers/settings.py
needlestack/utilities/__init__.py
needlestack/utilities/rpc.py
tests/__init__.py
tests/conftest.py
needlestack-0.1.0.dist-info/LICENSE
needlestack-0.1.0.dist-info/METADATA
needlestack-0.1.0.dist-info/WHEEL
needlestack-0.1.0.dist-info/top_level.txt
needlestack-0.1.0.dist-info/RECORD
