Metadata-Version: 2.1
Name: needlestack
Version: 0.1.0
Summary: A distributed vector search microservice.
Home-page: https://github.com/needlehaystack/needlestack
Author: Cung Tran
Author-email: minishcung@gmail.com
License: Apache License 2.0
Keywords: distributed nearest neighbors
Platform: UNKNOWN
Classifier: Development Status :: 4 - Beta
Classifier: Intended Audience :: Developers
Classifier: License :: OSI Approved :: Apache Software License
Classifier: Natural Language :: English
Classifier: Programming Language :: Python :: 3.6
Classifier: Programming Language :: Python :: 3.7
Requires-Dist: grpcio (>=1.18.0)
Requires-Dist: numpy (>=1.15.2)
Requires-Dist: protobuf (>=3.6.1)
Requires-Dist: kazoo (>=2.6.1)
Provides-Extra: faiss
Requires-Dist: faiss (==1.5.3) ; extra == 'faiss'
Provides-Extra: gcs
Requires-Dist: google-cloud-storage (==1.25.0) ; extra == 'gcs'
